{
  "version": 2,
  "tickRate": 66,
  "frames": [
    { "moveX": 0.00, "moveY": 1.0, "buttons": 0, "viewYawDeg": 8.0, "viewPitchDeg": -3.5 },
    { "moveX": 0.08, "moveY": 1.0, "buttons": 0, "viewYawDeg": 10.0, "viewPitchDeg": -3.4 },
    { "moveX": 0.15, "moveY": 1.0, "buttons": 0, "viewYawDeg": 12.0, "viewPitchDeg": -3.2 },
    { "moveX": 0.22, "moveY": 1.0, "buttons": 0, "viewYawDeg": 14.5, "viewPitchDeg": -3.0 },
    { "moveX": 0.28, "moveY": 1.0, "buttons": 1, "viewYawDeg": 16.0, "viewPitchDeg": -2.8 },
    { "moveX": 0.32, "moveY": 1.0, "buttons": 0, "viewYawDeg": 18.0, "viewPitchDeg": -2.6 },
    { "moveX": 0.35, "moveY": 1.0, "buttons": 0, "viewYawDeg": 19.0, "viewPitchDeg": -2.5 },
    { "moveX": 0.30, "moveY": 1.0, "buttons": 0, "viewYawDeg": 18.0, "viewPitchDeg": -2.7 },
    { "moveX": 0.18, "moveY": 1.0, "buttons": 0, "viewYawDeg": 15.0, "viewPitchDeg": -3.0 },
    { "moveX": 0.05, "moveY": 1.0, "buttons": 4, "viewYawDeg": 11.0, "viewPitchDeg": -3.5 },
    { "moveX": -0.08, "moveY": 1.0, "buttons": 0, "viewYawDeg": 7.0, "viewPitchDeg": -3.8 },
    { "moveX": -0.18, "moveY": 1.0, "buttons": 0, "viewYawDeg": 3.0, "viewPitchDeg": -4.0 },
    { "moveX": -0.26, "moveY": 1.0, "buttons": 0, "viewYawDeg": 0.0, "viewPitchDeg": -4.1 },
    { "moveX": -0.32, "moveY": 1.0, "buttons": 2, "viewYawDeg": -3.0, "viewPitchDeg": -4.2 },
    { "moveX": -0.35, "moveY": 1.0, "buttons": 2, "viewYawDeg": -6.0, "viewPitchDeg": -4.0 },
    { "moveX": -0.30, "moveY": 1.0, "buttons": 2, "viewYawDeg": -8.5, "viewPitchDeg": -3.9 },
    { "moveX": -0.18, "moveY": 1.0, "buttons": 0, "viewYawDeg": -10.0, "viewPitchDeg": -3.7 },
    { "moveX": -0.06, "moveY": 1.0, "buttons": 0, "viewYawDeg": -11.0, "viewPitchDeg": -3.5 },
    { "moveX": 0.06, "moveY": 1.0, "buttons": 0, "viewYawDeg": -9.5, "viewPitchDeg": -3.4 },
    { "moveX": 0.16, "moveY": 1.0, "buttons": 0, "viewYawDeg": -7.0, "viewPitchDeg": -3.3 },
    { "moveX": 0.24, "moveY": 1.0, "buttons": 0, "viewYawDeg": -4.0, "viewPitchDeg": -3.2 },
    { "moveX": 0.29, "moveY": 1.0, "buttons": 0, "viewYawDeg": -1.0, "viewPitchDeg": -3.1 },
    { "moveX": 0.18, "moveY": 1.0, "buttons": 0, "viewYawDeg": 2.5, "viewPitchDeg": -3.2 },
    { "moveX": 0.00, "moveY": 1.0, "buttons": 0, "viewYawDeg": 6.0, "viewPitchDeg": -3.4 }
  ]
}
